Workbook

Sheet Instrucciones
A1: Laboratorio 17 · Buscador y resumen
A3: Hojas: Productos, Ventas, Buscador y Resumen.
A5: Lo que debes hacer
A6: 1. Buscador!C4:C6: producto, categoría y precio del código de C2 con BUSCARX (cuarto argumento «No existe»).
A7: 2. Buscador!C7: rango de precio con SI.CONJUNTO (Premium ≥60, Clásico ≥40, Básico).
A8: 3. Resumen!B2:G4: ventas por sucursal y categoría con SUMAR.SI.CONJUNTO.
A9: 4. Nivel Experto: C6 con INDICE+COINCIDIR y C9 con FILTRAR (productos de la misma categoría).
A11: Importante: no cambies los nombres de las hojas ni muevas los datos de lugar. Al terminar, guarda el libro y súbelo en la página del módulo (etapa 4).

Sheet Productos
A1: Código | B1: Producto | C1: Categoría | D1: Precio | E1: Costo
A2: CAF-001 | B2: Espresso | C2: Café caliente | D2: 35 | E2: 8
A3: CAF-002 | B3: Americano | C3: Café caliente | D3: 40 | E3: 9
A4: CAF-003 | B4: Capuchino | C4: Café caliente | D4: 52 | E4: 13
A5: CAF-004 | B5: Latte | C5: Café caliente | D5: 55 | E5: 14
A6: CAF-005 | B6: Moka | C6: Café caliente | D6: 60 | E6: 16
A7: CAF-006 | B7: Café de olla | C7: Café caliente | D7: 38 | E7: 8
A8: FRI-001 | B8: Frappé moka | C8: Café frío | D8: 68 | E8: 18
A9: FRI-002 | B9: Cold brew | C9: Café frío | D9: 58 | E9: 12
A10: FRI-003 | B10: Latte helado | C10: Café frío | D10: 58 | E10: 15
A11: TE-001 | B11: Chai latte | C11: Té | D11: 54 | E11: 14
A12: TE-002 | B12: Té verde | C12: Té | D12: 38 | E12: 7
A13: PAN-001 | B13: Croissant | C13: Panadería | D13: 38 | E13: 12
... A21: ALI-002 | B21: Panini caprese | C21: Alimentos | D21: 85 | E21: 32

Sheet Ventas
A1: Folio | B1: Fecha | C1: Sucursal | D1: Código | E1: Producto | F1: Categoría | G1: Cantidad | H1: Precio | I1: Total | J1: Vendedor | K1: Pago
A2: V-0001 | B2: 45658 | C2: Norte | D2: POS-002 | E2: Brownie | F2: Postres | G2: 23 | H2: 40 | I2: 920 | J2: Mariana Paredes | K2: Tarjeta
A3: V-0002 | B3: 45658 | C3: Sur | D3: PAN-001 | E3: Croissant | F3: Panadería | G3: 31 | H3: 38 | I3: 1178 | J3: Regina Fuentes | K3: Tarjeta
A4: V-0003 | B4: 45658 | C4: Sur | D4: PAN-002 | E4: Concha | F4: Panadería | G4: 28 | H4: 22 | I4: 616 | J4: Pablo Aguilar | K4: Tarjeta
A5: V-0004 | B5: 45659 | C5: Sur | D5: ALI-001 | E5: Sándwich de pavo | F5: Alimentos | G5: 31 | H5: 78 | I5: 2418 | J5: Valeria Ochoa | K5: Tarjeta
A6: V-0005 | B6: 45659 | C6: Sur | D6: CAF-001 | E6: Espresso | F6: Café caliente | G6: 14 | H6: 35 | I6: 490 | J6: Tania Guzmán | K6: Tarjeta
A7: V-0006 | B7: 45660 | C7: Sur | D7: PAN-004 | E7: Bagel con queso crema | F7: Panadería | G7: 32 | H7: 45 | I7: 1440 | J7: Sergio Mendoza | K7: Transferencia
A8: V-0007 | B8: 45661 | C8: Centro | D8: FRI-001 | E8: Frappé moka | F8: Café frío | G8: 27 | H8: 68 | I8: 1836 | J8: Elena Robles | K8: Efectivo
A9: V-0008 | B9: 45661 | C9: Norte | D9: CAF-003 | E9: Capuchino | F9: Café caliente | G9: 28 | H9: 52 | I9: 1456 | J9: Leonardo Ríos | K9: Efectivo
A10: V-0009 | B10: 45661 | C10: Sur | D10: CAF-005 | E10: Moka | F10: Café caliente | G10: 21 | H10: 60 | I10: 1260 | J10: Tania Guzmán | K10: Transferencia
A11: V-0010 | B11: 45664 | C11: Centro | D11: CAF-002 | E11: Americano | F11: Café caliente | G11: 48 | H11: 40 | I11: 1920 | J11: Andrea Solís | K11: Tarjeta
A12: V-0011 | B12: 45664 | C12: Norte | D12: PAN-001 | E12: Croissant | F12: Panadería | G12: 31 | H12: 38 | I12: 1178 | J12: Leonardo Ríos | K12: Transferencia
A13: V-0012 | B13: 45664 | C13: Norte | D13: POS-003 | E13: Galleta de avena | F13: Postres | G13: 26 | H13: 25 | I13: 650 | J13: Mariana Paredes | K13: Efectivo
... A721: V-0720 | B721: 46021 | C721: Norte | D721: PAN-002 | E721: Concha | F721: Panadería | G721: 40 | H721: 22 | I721: 880 | J721: Héctor Vargas | K721: Tarjeta

Sheet Buscador
B1: Buscador de productos
B2: Código: | C2: CAF-004
B4: Producto | C4: =_xlfn.XLOOKUP(C2,Productos!A2:A21,Productos!B2:B21,"No existe")
B5: Categoría | C5: =_xlfn.XLOOKUP(C2,Productos!A2:A21,Productos!C2:C21,"No existe")
B6: Precio | C6: =INDEX(Productos!D2:D21,MATCH(C2,Productos!A2:A21,0))
B7: Rango de precio | C7: =_xlfn.IFS(C6>=60,"Premium",C6>=40,"Clásico",TRUE,"Básico")
B9: Misma categoría

Sheet Resumen
A1: Sucursal \ Categoría | B1: Café caliente | C1: Café frío | D1: Té | E1: Panadería | F1: Postres | G1: Alimentos
A2: Centro | B2: =SUMIFS(Ventas!$I:$I,Ventas!$C:$C,$A2,Ventas!$F:$F,B$1) | C2: =SUMIFS(Ventas!$I:$I,Ventas!$C:$C,$A2,Ventas!$F:$F,C$1) | D2: =SUMIFS(Ventas!$I:$I,Ventas!$C:$C,$A2,Ventas!$F:$F,D$1) | E2: =SUMIFS(Ventas!$I:$I,Ventas!$C:$C,$A2,Ventas!$F:$F,E$1) | F2: =SUMIFS(Ventas!$I:$I,Ventas!$C:$C,$A2,Ventas!$F:$F,F$1) | G2: =SUMIFS(Ventas!$I:$I,Ventas!$C:$C,$A2,Ventas!$F:$F,G$1)
A3: Norte | B3: =SUMIFS(Ventas!$I:$I,Ventas!$C:$C,$A3,Ventas!$F:$F,B$1) | C3: =SUMIFS(Ventas!$I:$I,Ventas!$C:$C,$A3,Ventas!$F:$F,C$1) | D3: =SUMIFS(Ventas!$I:$I,Ventas!$C:$C,$A3,Ventas!$F:$F,D$1) | E3: =SUMIFS(Ventas!$I:$I,Ventas!$C:$C,$A3,Ventas!$F:$F,E$1) | F3: =SUMIFS(Ventas!$I:$I,Ventas!$C:$C,$A3,Ventas!$F:$F,F$1) | G3: =SUMIFS(Ventas!$I:$I,Ventas!$C:$C,$A3,Ventas!$F:$F,G$1)
A4: Sur | B4: =SUMIFS(Ventas!$I:$I,Ventas!$C:$C,$A4,Ventas!$F:$F,B$1) | C4: =SUMIFS(Ventas!$I:$I,Ventas!$C:$C,$A4,Ventas!$F:$F,C$1) | D4: =SUMIFS(Ventas!$I:$I,Ventas!$C:$C,$A4,Ventas!$F:$F,D$1) | E4: =SUMIFS(Ventas!$I:$I,Ventas!$C:$C,$A4,Ventas!$F:$F,E$1) | F4: =SUMIFS(Ventas!$I:$I,Ventas!$C:$C,$A4,Ventas!$F:$F,F$1) | G4: =SUMIFS(Ventas!$I:$I,Ventas!$C:$C,$A4,Ventas!$F:$F,G$1)

Sheet Solución
A1: Solución paso a paso (para el docente)
A3: C9 (Experto): =FILTRAR(Productos!B2:B21, Productos!C2:C21=C5). openpyxl no escribe matrices dinámicas: escríbela en Excel.
